{
  "cap_id": "map to Zap Meta Timestamp",
  "timestamp": "map to Zap Meta Human Now",
  "domain": "Research",
  "context_mode": "Advisor",
  "ems": 0.82,
  "cw": 0.18,
  "ad": 0.06,
  "hci": 0.71,
  "validator_id": "Athena-Core-Local",
  "validator_signature": "2aa4a3017c51595456cd501c2e484525e1a801614b4e066e1f613237accd91b4",
  "reasoning_summary": "Automated reasoning log from FalconForge Athena instance.",
  "ethical_flags": ["autogenerated", "public_source"],
  "content": "Hello_from_Athena_CAP_Test_working!"
}
